README.rst
setup.cfg
setup.py
cec2019comp100digit/__init__.py
cec2019comp100digit/cec19_func.cpp
cec2019comp100digit/cec19_func.h
cec2019comp100digit/cec2019comp100digit.pyx
cec2019comp100digit/eval_func.cpp
cec2019comp100digit/eval_func.h
cec2019comp100digit.egg-info/PKG-INFO
cec2019comp100digit.egg-info/SOURCES.txt
cec2019comp100digit.egg-info/dependency_links.txt
cec2019comp100digit.egg-info/requires.txt
cec2019comp100digit.egg-info/top_level.txt
cec2019comp100digit/input_data/M_10_D10.txt
cec2019comp100digit/input_data/M_10_D2.txt
cec2019comp100digit/input_data/M_1_D10.txt
cec2019comp100digit/input_data/M_1_D2.txt
cec2019comp100digit/input_data/M_2_D10.txt
cec2019comp100digit/input_data/M_2_D2.txt
cec2019comp100digit/input_data/M_3_D10.txt
cec2019comp100digit/input_data/M_3_D2.txt
cec2019comp100digit/input_data/M_4_D10.txt
cec2019comp100digit/input_data/M_4_D2.txt
cec2019comp100digit/input_data/M_5_D10.txt
cec2019comp100digit/input_data/M_5_D2.txt
cec2019comp100digit/input_data/M_6_D10.txt
cec2019comp100digit/input_data/M_6_D2.txt
cec2019comp100digit/input_data/M_7_D10.txt
cec2019comp100digit/input_data/M_7_D2.txt
cec2019comp100digit/input_data/M_8_D10.txt
cec2019comp100digit/input_data/M_8_D2.txt
cec2019comp100digit/input_data/M_8_D20.txt
cec2019comp100digit/input_data/M_9_D10.txt
cec2019comp100digit/input_data/M_9_D2.txt
cec2019comp100digit/input_data/shift_data_1.txt
cec2019comp100digit/input_data/shift_data_10.txt
cec2019comp100digit/input_data/shift_data_2.txt
cec2019comp100digit/input_data/shift_data_3.txt
cec2019comp100digit/input_data/shift_data_4.txt
cec2019comp100digit/input_data/shift_data_5.txt
cec2019comp100digit/input_data/shift_data_6.txt
cec2019comp100digit/input_data/shift_data_7.txt
cec2019comp100digit/input_data/shift_data_8.txt
cec2019comp100digit/input_data/shift_data_9.txt