Metadata-Version: 1.2
Name: cec2019comp100digit
Version: 0.7
Summary: Package for benchmark for the     100 digit competition on the IEEE     Congress on Evolutionary Computation CEC'2019
Home-page: https://github.com/dmolina/cec2019comp100digit
Author: Daniel Molina
Author-email: dmolina@decsai.ugr.es
Maintainer: Daniel Molina
License: GPL V3
Platform: UNKNOWN
Classifier: Development Status :: 5 - Production/Stable
Classifier: License :: OSI Approved :: GNU General Public License v3 or later (GPLv3+)
